pinns_sird/AB3.py
pinns_sird/AB3_Iteration.py
pinns_sird/AB3_solveSIRD.py
pinns_sird/AB3_testing.py
pinns_sird/Compartment_Models.py
pinns_sird/DNN_base.py
pinns_sird/DNN_tools.py
pinns_sird/Numeric_Methods.py
pinns_sird/__init__.py
pinns_sird/dataUtils.py
pinns_sird/logUtils.py
pinns_sird/plotData.py
pinns_sird/saveData.py
pinns_sird-0.1.3.dist-info/METADATA
pinns_sird-0.1.3.dist-info/WHEEL
pinns_sird-0.1.3.dist-info/top_level.txt
pinns_sird-0.1.3.dist-info/RECORD
